sspals/__init__.py
sspals/cfd.py
sspals/chmx.py
sspals/core.py
sspals/sim.py
sspals-0.1.2.dist-info/METADATA
sspals-0.1.2.dist-info/RECORD
sspals-0.1.2.dist-info/WHEEL
sspals-0.1.2.dist-info/top_level.txt
